[
    {
        "kind": "youtube#searchListResponse",
        "etag": "\"j6xRRd8dTPVVptg711_CSPADRfg/nMbWXkxUNTAhUmQYRyYRfClcnZk\"",
        "nextPageToken": "CAMQAA",
        "regionCode": "US",
        "pageInfo": {
            "totalResults": 116,
            "resultsPerPage": 3
        },
        "items": [
            {
                "kind": "youtube#searchResult",
                "etag": "\"j6xRRd8dTPVVptg711_CSPADRfg/ASBDqE9hoVZqXTtCHqfrLNIPxKg\"",
                "id": {
                    "kind": "youtube#video",
                    "videoId": "xsU10fX0aC0"
                },
                "snippet": {
                    "publishedAt": "2017-02-03T16:22:09.000Z",
                    "channelId": "UCAuUUnT6oDeKwE6v1NGQxug",
                    "title": "To solve old problems, study new species | Alejandro Sánchez Alvarado",
                    "description": "Nature is wonderfully abundant, diverse and mysterious -- but biological research today tends to focus on only seven species, including rats, chickens, fruit flies ...",
                    "thumbnails": {
                        "default": {
                            "url": "https://i.ytimg.com/vi/xsU10fX0aC0/default.jpg",
                            "width": 120,
                            "height": 90
                        },
                        "medium": {
                            "url": "https://i.ytimg.com/vi/xsU10fX0aC0/mqdefault.jpg",
                            "width": 320,
                            "height": 180
                        },
                        "high": {
                            "url": "https://i.ytimg.com/vi/xsU10fX0aC0/hqdefault.jpg",
                            "width": 480,
                            "height": 360
                        }
                    },
                    "channelTitle": "TED",
                    "liveBroadcastContent": "none"
                },
                "stats": {
                    "kind": "youtube#videoListResponse",
                    "etag": "\"j6xRRd8dTPVVptg711_CSPADRfg/MHI7PlRf8HvC97-gydKHEl0OL4U\"",
                    "pageInfo": {
                        "totalResults": 1,
                        "resultsPerPage": 1
                    },
                    "items": [
                        {
                            "kind": "youtube#video",
                            "etag": "\"j6xRRd8dTPVVptg711_CSPADRfg/_tmN4M2cx-I2SoLTqDJ9oMQoi58\"",
                            "id": "xsU10fX0aC0",
                            "statistics": {
                                "viewCount": "102520",
                                "likeCount": "2475",
                                "dislikeCount": "56",
                                "favoriteCount": "0",
                                "commentCount": "98"
                            }
                        }
                    ]
                }
            },
            {
                "kind": "youtube#searchResult",
                "etag": "\"j6xRRd8dTPVVptg711_CSPADRfg/LOqdgrKATjU16ngm_1IYsjKHVqU\"",
                "id": {
                    "kind": "youtube#video",
                    "videoId": "_Wj_KTraw7c"
                },
                "snippet": {
                    "publishedAt": "2016-08-31T17:05:56.000Z",
                    "channelId": "UCsT0YIqwnpJCM-mx7-gSA4Q",
                    "title": "Life On This Planet Is The History Of Rule Breakers | Alejandro Sánchez Alvarado | TEDxKC",
                    "description": "This fascinating talk poses the question: is the way science approaches life's biggest mysteries restricting our ability to solve them? Life on this planet is the ...",
                    "thumbnails": {
                        "default": {
                            "url": "https://i.ytimg.com/vi/_Wj_KTraw7c/default.jpg",
                            "width": 120,
                            "height": 90
                        },
                        "medium": {
                            "url": "https://i.ytimg.com/vi/_Wj_KTraw7c/mqdefault.jpg",
                            "width": 320,
                            "height": 180
                        },
                        "high": {
                            "url": "https://i.ytimg.com/vi/_Wj_KTraw7c/hqdefault.jpg",
                            "width": 480,
                            "height": 360
                        }
                    },
                    "channelTitle": "TEDx Talks",
                    "liveBroadcastContent": "none"
                },
                "stats": {
                    "kind": "youtube#videoListResponse",
                    "etag": "\"j6xRRd8dTPVVptg711_CSPADRfg/W-Xj7xK30GKOWQ_0dQeAKSQUFa8\"",
                    "pageInfo": {
                        "totalResults": 1,
                        "resultsPerPage": 1
                    },
                    "items": [
                        {
                            "kind": "youtube#video",
                            "etag": "\"j6xRRd8dTPVVptg711_CSPADRfg/Tfe_9YT8y0hruHzPFYAZOe9AZRM\"",
                            "id": "_Wj_KTraw7c",
                            "statistics": {
                                "viewCount": "5428",
                                "likeCount": "82",
                                "dislikeCount": "4",
                                "favoriteCount": "0",
                                "commentCount": "8"
                            }
                        }
                    ]
                }
            },
            {
                "kind": "youtube#searchResult",
                "etag": "\"j6xRRd8dTPVVptg711_CSPADRfg/7eKNIsaVLDYH3aON76e2fbK81Jw\"",
                "id": {
                    "kind": "youtube#video",
                    "videoId": "FDlg4aHBfl0"
                },
                "snippet": {
                    "publishedAt": "2016-05-16T23:24:46.000Z",
                    "channelId": "UCsvqEZBO-kNmwuDBbKbfL6A",
                    "title": "Alejandro Sánchez Alvarado (Stowers, HHMI) 1: Scale, proportion and organ regeneration",
                    "description": "https://www.ibiology.org/development-and-stem-cells/planarian/ Outline: During growth and regeneration, planarians face intrinsic problems of scale and ...",
                    "thumbnails": {
                        "default": {
                            "url": "https://i.ytimg.com/vi/FDlg4aHBfl0/default.jpg",
                            "width": 120,
                            "height": 90
                        },
                        "medium": {
                            "url": "https://i.ytimg.com/vi/FDlg4aHBfl0/mqdefault.jpg",
                            "width": 320,
                            "height": 180
                        },
                        "high": {
                            "url": "https://i.ytimg.com/vi/FDlg4aHBfl0/hqdefault.jpg",
                            "width": 480,
                            "height": 360
                        }
                    },
                    "channelTitle": "iBiology",
                    "liveBroadcastContent": "none"
                },
                "stats": {
                    "kind": "youtube#videoListResponse",
                    "etag": "\"j6xRRd8dTPVVptg711_CSPADRfg/rtXgahQesbl0nhyl0QJMIkzKKlU\"",
                    "pageInfo": {
                        "totalResults": 1,
                        "resultsPerPage": 1
                    },
                    "items": [
                        {
                            "kind": "youtube#video",
                            "etag": "\"j6xRRd8dTPVVptg711_CSPADRfg/jctDmwlAQHg4E3yv8XKldCCEG2E\"",
                            "id": "FDlg4aHBfl0",
                            "statistics": {
                                "viewCount": "3850",
                                "likeCount": "43",
                                "dislikeCount": "1",
                                "favoriteCount": "0",
                                "commentCount": "4"
                            }
                        }
                    ]
                }
            }
        ],
        "originalQuery": "Alejandro Sánchez Alvarado: To solve old problems, study new species"
    },
    {
        "kind": "youtube#searchListResponse",
        "etag": "\"j6xRRd8dTPVVptg711_CSPADRfg/hD7spxvxAxEvsWp3rrPMvAMBudY\"",
        "nextPageToken": "CAMQAA",
        "regionCode": "US",
        "pageInfo": {
            "totalResults": 174,
            "resultsPerPage": 3
        },
        "items": [
            {
                "kind": "youtube#searchResult",
                "etag": "\"j6xRRd8dTPVVptg711_CSPADRfg/KrDU8nhLfbkueSl4FFS42tZ1HiI\"",
                "id": {
                    "kind": "youtube#video",
                    "videoId": "waRC-CQnoeY"
                },
                "snippet": {
                    "publishedAt": "2017-02-02T20:07:03.000Z",
                    "channelId": "UCAuUUnT6oDeKwE6v1NGQxug",
                    "title": "If a story moves you, act on it | Sisonke Msimang",
                    "description": "Stories are necessary, but they're not as magical as they seem, says writer Sisonke Msimang. In this funny and thoughtful talk, Msimang questions our emphasis ...",
                    "thumbnails": {
                        "default": {
                            "url": "https://i.ytimg.com/vi/waRC-CQnoeY/default.jpg",
                            "width": 120,
                            "height": 90
                        },
                        "medium": {
                            "url": "https://i.ytimg.com/vi/waRC-CQnoeY/mqdefault.jpg",
                            "width": 320,
                            "height": 180
                        },
                        "high": {
                            "url": "https://i.ytimg.com/vi/waRC-CQnoeY/hqdefault.jpg",
                            "width": 480,
                            "height": 360
                        }
                    },
                    "channelTitle": "TED",
                    "liveBroadcastContent": "none"
                },
                "stats": {
                    "kind": "youtube#videoListResponse",
                    "etag": "\"j6xRRd8dTPVVptg711_CSPADRfg/OA_7KWTdcNlpv1f4xABuhxTLFXw\"",
                    "pageInfo": {
                        "totalResults": 1,
                        "resultsPerPage": 1
                    },
                    "items": [
                        {
                            "kind": "youtube#video",
                            "etag": "\"j6xRRd8dTPVVptg711_CSPADRfg/eOY1Kl3rSftwwyPgSdXde2ebW04\"",
                            "id": "waRC-CQnoeY",
                            "statistics": {
                                "viewCount": "88671",
                                "likeCount": "2821",
                                "dislikeCount": "380",
                                "favoriteCount": "0",
                                "commentCount": "207"
                            }
                        }
                    ]
                }
            },
            {
                "kind": "youtube#searchResult",
                "etag": "\"j6xRRd8dTPVVptg711_CSPADRfg/Id_J7tU0sKMU0Bol_2PxrPFXLW4\"",
                "id": {
                    "kind": "youtube#video",
                    "videoId": "T5lE9Z-nRQg"
                },
                "snippet": {
                    "publishedAt": "2016-09-22T20:28:51.000Z",
                    "channelId": "UCxw-YwaBR9lVa1fmreWy94g",
                    "title": "The Moth Presents: Sisonke Msimang",
                    "description": "An idealistic woman learns about the power of listening from a friend. Sisonke Msimang is a writer and activist whose work focuses on money, power, and sex.",
                    "thumbnails": {
                        "default": {
                            "url": "https://i.ytimg.com/vi/T5lE9Z-nRQg/default.jpg",
                            "width": 120,
                            "height": 90
                        },
                        "medium": {
                            "url": "https://i.ytimg.com/vi/T5lE9Z-nRQg/mqdefault.jpg",
                            "width": 320,
                            "height": 180
                        },
                        "high": {
                            "url": "https://i.ytimg.com/vi/T5lE9Z-nRQg/hqdefault.jpg",
                            "width": 480,
                            "height": 360
                        }
                    },
                    "channelTitle": "The Moth",
                    "liveBroadcastContent": "none"
                },
                "stats": {
                    "kind": "youtube#videoListResponse",
                    "etag": "\"j6xRRd8dTPVVptg711_CSPADRfg/xhx4QLPU42pTO-cU77kw1lX4MHQ\"",
                    "pageInfo": {
                        "totalResults": 1,
                        "resultsPerPage": 1
                    },
                    "items": [
                        {
                            "kind": "youtube#video",
                            "etag": "\"j6xRRd8dTPVVptg711_CSPADRfg/wHoZOyN6KuzJXEpnSog5xfBbHAI\"",
                            "id": "T5lE9Z-nRQg",
                            "statistics": {
                                "viewCount": "21445",
                                "likeCount": "290",
                                "dislikeCount": "8",
                                "favoriteCount": "0"
                            }
                        }
                    ]
                }
            },
            {
                "kind": "youtube#searchResult",
                "etag": "\"j6xRRd8dTPVVptg711_CSPADRfg/Glqfeph7SOMrFzJ7R5YpMRdb1FY\"",
                "id": {
                    "kind": "youtube#video",
                    "videoId": "B9LF8Uy6ppI"
                },
                "snippet": {
                    "publishedAt": "2017-02-09T13:24:26.000Z",
                    "channelId": "UCQiasQLkRboZdoLjSdD7iSQ",
                    "title": "Mauyinja  - Sisonke (Official Music Video)",
                    "description": "Rap,recorded 2013,Shot 2016.",
                    "thumbnails": {
                        "default": {
                            "url": "https://i.ytimg.com/vi/B9LF8Uy6ppI/default.jpg",
                            "width": 120,
                            "height": 90
                        },
                        "medium": {
                            "url": "https://i.ytimg.com/vi/B9LF8Uy6ppI/mqdefault.jpg",
                            "width": 320,
                            "height": 180
                        },
                        "high": {
                            "url": "https://i.ytimg.com/vi/B9LF8Uy6ppI/hqdefault.jpg",
                            "width": 480,
                            "height": 360
                        }
                    },
                    "channelTitle": "Mauyinja- Uyinja",
                    "liveBroadcastContent": "none"
                },
                "stats": {
                    "kind": "youtube#videoListResponse",
                    "etag": "\"j6xRRd8dTPVVptg711_CSPADRfg/vfsgxtVdekWz0__8TRVcwUmTZ2U\"",
                    "pageInfo": {
                        "totalResults": 1,
                        "resultsPerPage": 1
                    },
                    "items": [
                        {
                            "kind": "youtube#video",
                            "etag": "\"j6xRRd8dTPVVptg711_CSPADRfg/8920CESSFIX1HoSDOkHo7LnKdn8\"",
                            "id": "B9LF8Uy6ppI",
                            "statistics": {
                                "viewCount": "231",
                                "likeCount": "10",
                                "dislikeCount": "0",
                                "favoriteCount": "0",
                                "commentCount": "3"
                            }
                        }
                    ]
                }
            }
        ],
        "originalQuery": "Sisonke Msimang: If a story moves you, act on it"
    },
    {
        "kind": "youtube#searchListResponse",
        "etag": "\"j6xRRd8dTPVVptg711_CSPADRfg/fhhmzUzHTZQEA8VYsO_ZYI0qAHY\"",
        "nextPageToken": "CAMQAA",
        "regionCode": "US",
        "pageInfo": {
            "totalResults": 649,
            "resultsPerPage": 3
        },
        "items": [
            {
                "kind": "youtube#searchResult",
                "etag": "\"j6xRRd8dTPVVptg711_CSPADRfg/orxKrmbR0I5d7ihZlf7M0AtZIfU\"",
                "id": {
                    "kind": "youtube#video",
                    "videoId": "Fb3yp4uJhq0"
                },
                "snippet": {
                    "publishedAt": "2017-01-17T20:45:10.000Z",
                    "channelId": "UCAuUUnT6oDeKwE6v1NGQxug",
                    "title": "What happens when you have a disease doctors can&#39;t diagnose | Jennifer Brea",
                    "description": "Five years ago, TED Fellow Jen Brea became progressively ill with myalgic encephalomyelitis, commonly known as chronic fatigue syndrome, a debilitating ...",
                    "thumbnails": {
                        "default": {
                            "url": "https://i.ytimg.com/vi/Fb3yp4uJhq0/default.jpg",
                            "width": 120,
                            "height": 90
                        },
                        "medium": {
                            "url": "https://i.ytimg.com/vi/Fb3yp4uJhq0/mqdefault.jpg",
                            "width": 320,
                            "height": 180
                        },
                        "high": {
                            "url": "https://i.ytimg.com/vi/Fb3yp4uJhq0/hqdefault.jpg",
                            "width": 480,
                            "height": 360
                        }
                    },
                    "channelTitle": "TED",
                    "liveBroadcastContent": "none"
                },
                "stats": {
                    "kind": "youtube#videoListResponse",
                    "etag": "\"j6xRRd8dTPVVptg711_CSPADRfg/D_Xwu8wpFo-Fx0Tg0DJCUfDBQ5Q\"",
                    "pageInfo": {
                        "totalResults": 1,
                        "resultsPerPage": 1
                    },
                    "items": [
                        {
                            "kind": "youtube#video",
                            "etag": "\"j6xRRd8dTPVVptg711_CSPADRfg/TsexAIpJIGhn6iJJRFrChDPtNxc\"",
                            "id": "Fb3yp4uJhq0",
                            "statistics": {
                                "viewCount": "647762",
                                "likeCount": "21307",
                                "dislikeCount": "457",
                                "favoriteCount": "0",
                                "commentCount": "2345"
                            }
                        }
                    ]
                }
            },
            {
                "kind": "youtube#searchResult",
                "etag": "\"j6xRRd8dTPVVptg711_CSPADRfg/fVbx21YBNzvgj8l-GSD_yufqIIg\"",
                "id": {
                    "kind": "youtube#video",
                    "videoId": "ZRAM7Q2nx10"
                },
                "snippet": {
                    "publishedAt": "2017-10-29T01:30:52.000Z",
                    "channelId": "UCDLzNae5E3eJpWR2tFg1Ktw",
                    "title": "Jen Brea and Charles Shepherd interviewed about Unrest - CFS/ME",
                    "description": "Jennifer Brea, film producer and dr. Charles Shepherd are interviewed on BBC about the movie \"Unrest\". The documentary follows Brea, a sufferer of the chronic ...",
                    "thumbnails": {
                        "default": {
                            "url": "https://i.ytimg.com/vi/ZRAM7Q2nx10/default.jpg",
                            "width": 120,
                            "height": 90
                        },
                        "medium": {
                            "url": "https://i.ytimg.com/vi/ZRAM7Q2nx10/mqdefault.jpg",
                            "width": 320,
                            "height": 180
                        },
                        "high": {
                            "url": "https://i.ytimg.com/vi/ZRAM7Q2nx10/hqdefault.jpg",
                            "width": 480,
                            "height": 360
                        }
                    },
                    "channelTitle": "Jan Hansen",
                    "liveBroadcastContent": "none"
                },
                "stats": {
                    "kind": "youtube#videoListResponse",
                    "etag": "\"j6xRRd8dTPVVptg711_CSPADRfg/1D-S44irnOoo41sI-EjRDcVsaMY\"",
                    "pageInfo": {
                        "totalResults": 1,
                        "resultsPerPage": 1
                    },
                    "items": [
                        {
                            "kind": "youtube#video",
                            "etag": "\"j6xRRd8dTPVVptg711_CSPADRfg/IyUkseNd5NaIC-wPzNyNvsEPuMk\"",
                            "id": "ZRAM7Q2nx10",
                            "statistics": {
                                "viewCount": "33296",
                                "likeCount": "458",
                                "dislikeCount": "15",
                                "favoriteCount": "0",
                                "commentCount": "117"
                            }
                        }
                    ]
                }
            },
            {
                "kind": "youtube#searchResult",
                "etag": "\"j6xRRd8dTPVVptg711_CSPADRfg/T4qg-bNd1isJtCvjmk30am8oFBE\"",
                "id": {
                    "kind": "youtube#video",
                    "videoId": "pwFirXs4glA"
                },
                "snippet": {
                    "publishedAt": "2017-09-28T18:16:26.000Z",
                    "channelId": "UChDKyKQ59fYz3JO2fl0Z6sg",
                    "title": "Filmmaker Opens Up About Illness That Doctors Told Her Was ‘All In Her Head’ | Megyn Kelly TODAY",
                    "description": "Jennifer Brea was on her way to earning a doctorate from Harvard when she was stricken with an illness that doctors said was “all in her head.” She is joined live ...",
                    "thumbnails": {
                        "default": {
                            "url": "https://i.ytimg.com/vi/pwFirXs4glA/default.jpg",
                            "width": 120,
                            "height": 90
                        },
                        "medium": {
                            "url": "https://i.ytimg.com/vi/pwFirXs4glA/mqdefault.jpg",
                            "width": 320,
                            "height": 180
                        },
                        "high": {
                            "url": "https://i.ytimg.com/vi/pwFirXs4glA/hqdefault.jpg",
                            "width": 480,
                            "height": 360
                        }
                    },
                    "channelTitle": "TODAY",
                    "liveBroadcastContent": "none"
                },
                "stats": {
                    "kind": "youtube#videoListResponse",
                    "etag": "\"j6xRRd8dTPVVptg711_CSPADRfg/7G6QHl1aHHwNED9GvbzRHWl4HHA\"",
                    "pageInfo": {
                        "totalResults": 1,
                        "resultsPerPage": 1
                    },
                    "items": [
                        {
                            "kind": "youtube#video",
                            "etag": "\"j6xRRd8dTPVVptg711_CSPADRfg/_nKUzN6gwHbxmRzpS2MaucgbOfQ\"",
                            "id": "pwFirXs4glA",
                            "statistics": {
                                "viewCount": "38101",
                                "likeCount": "456",
                                "dislikeCount": "27",
                                "favoriteCount": "0",
                                "commentCount": "129"
                            }
                        }
                    ]
                }
            }
        ],
        "originalQuery": "Jennifer Brea: What happens when you have a disease doctors can't diagnose"
    },
    {
        "kind": "youtube#searchListResponse",
        "etag": "\"j6xRRd8dTPVVptg711_CSPADRfg/Rqxok0X3O0sH8X-lyawcx5lVHEg\"",
        "nextPageToken": "CAMQAA",
        "regionCode": "US",
        "pageInfo": {
            "totalResults": 264,
            "resultsPerPage": 3
        },
        "items": [
            {
                "kind": "youtube#searchResult",
                "etag": "\"j6xRRd8dTPVVptg711_CSPADRfg/J-08bM57x2dr3qrlb6Ii1vCtsEY\"",
                "id": {
                    "kind": "youtube#video",
                    "videoId": "GSf6nij-SdA"
                },
                "snippet": {
                    "publishedAt": "2017-01-18T16:01:57.000Z",
                    "channelId": "UCAuUUnT6oDeKwE6v1NGQxug",
                    "title": "How online abuse of women has spiraled out of control | Ashley Judd",
                    "description": "Enough with online hate speech, sexual harassment and threats of violence against women and marginalized groups. It's time to take the global crisis of online ...",
                    "thumbnails": {
                        "default": {
                            "url": "https://i.ytimg.com/vi/GSf6nij-SdA/default.jpg",
                            "width": 120,
                            "height": 90
                        },
                        "medium": {
                            "url": "https://i.ytimg.com/vi/GSf6nij-SdA/mqdefault.jpg",
                            "width": 320,
                            "height": 180
                        },
                        "high": {
                            "url": "https://i.ytimg.com/vi/GSf6nij-SdA/hqdefault.jpg",
                            "width": 480,
                            "height": 360
                        }
                    },
                    "channelTitle": "TED",
                    "liveBroadcastContent": "none"
                },
                "stats": {
                    "kind": "youtube#videoListResponse",
                    "etag": "\"j6xRRd8dTPVVptg711_CSPADRfg/iVtFd8s6ne3N79RYJGaZ8ORJ5So\"",
                    "pageInfo": {
                        "totalResults": 1,
                        "resultsPerPage": 1
                    },
                    "items": [
                        {
                            "kind": "youtube#video",
                            "etag": "\"j6xRRd8dTPVVptg711_CSPADRfg/ZmY-NFb0855h321_OYRRzXnKx4M\"",
                            "id": "GSf6nij-SdA",
                            "statistics": {
                                "viewCount": "290965",
                                "favoriteCount": "0"
                            }
                        }
                    ]
                }
            },
            {
                "kind": "youtube#searchResult",
                "etag": "\"j6xRRd8dTPVVptg711_CSPADRfg/Jxn9tsYLx1zxBqg4FE-UMHQ_bvQ\"",
                "id": {
                    "kind": "youtube#video",
                    "videoId": "20oHTRhq464"
                },
                "snippet": {
                    "publishedAt": "2019-03-07T17:16:19.000Z",
                    "channelId": "UCwyKZWhsD2YFg8huOaO3IOg",
                    "title": "CPDP 2019 - &#39;Online abuse of women: Who is fighting back?&#39;",
                    "description": "Video courtesy of CPDP (https://www.cpdpconferences.org/) What is the impact of online gender-based violence on survivors? What should be the role of ...",
                    "thumbnails": {
                        "default": {
                            "url": "https://i.ytimg.com/vi/20oHTRhq464/default.jpg",
                            "width": 120,
                            "height": 90
                        },
                        "medium": {
                            "url": "https://i.ytimg.com/vi/20oHTRhq464/mqdefault.jpg",
                            "width": 320,
                            "height": 180
                        },
                        "high": {
                            "url": "https://i.ytimg.com/vi/20oHTRhq464/hqdefault.jpg",
                            "width": 480,
                            "height": 360
                        }
                    },
                    "channelTitle": "Privacy International",
                    "liveBroadcastContent": "none"
                },
                "stats": {
                    "kind": "youtube#videoListResponse",
                    "etag": "\"j6xRRd8dTPVVptg711_CSPADRfg/W5SBvyKRlqozaxVNdCYjEt8I0NY\"",
                    "pageInfo": {
                        "totalResults": 1,
                        "resultsPerPage": 1
                    },
                    "items": [
                        {
                            "kind": "youtube#video",
                            "etag": "\"j6xRRd8dTPVVptg711_CSPADRfg/6Sm1lfCT8JYHcV6-51NDPypco-c\"",
                            "id": "20oHTRhq464",
                            "statistics": {
                                "viewCount": "39",
                                "likeCount": "1",
                                "dislikeCount": "1",
                                "favoriteCount": "0",
                                "commentCount": "0"
                            }
                        }
                    ]
                }
            },
            {
                "kind": "youtube#searchResult",
                "etag": "\"j6xRRd8dTPVVptg711_CSPADRfg/qq65lGRv1YeGB4gP_06z0lY1TQA\"",
                "id": {
                    "kind": "youtube#video",
                    "videoId": "t7sNVRlr4CQ"
                },
                "snippet": {
                    "publishedAt": "2018-10-22T18:33:13.000Z",
                    "channelId": "UCK7tptUDHh-RYDsdxO1-5QQ",
                    "title": "Online Harassment: How Victims Are Fighting Back | Moving Upstream",
                    "description": "Roughly 40% of Americans say they've experienced some form of online harassment. For some, these threats can become extreme, making it impossible to lead ...",
                    "thumbnails": {
                        "default": {
                            "url": "https://i.ytimg.com/vi/t7sNVRlr4CQ/default.jpg",
                            "width": 120,
                            "height": 90
                        },
                        "medium": {
                            "url": "https://i.ytimg.com/vi/t7sNVRlr4CQ/mqdefault.jpg",
                            "width": 320,
                            "height": 180
                        },
                        "high": {
                            "url": "https://i.ytimg.com/vi/t7sNVRlr4CQ/hqdefault.jpg",
                            "width": 480,
                            "height": 360
                        }
                    },
                    "channelTitle": "Wall Street Journal",
                    "liveBroadcastContent": "none"
                },
                "stats": {
                    "kind": "youtube#videoListResponse",
                    "etag": "\"j6xRRd8dTPVVptg711_CSPADRfg/OCYO3dibCuZrM-oYMqd3lpITWBg\"",
                    "pageInfo": {
                        "totalResults": 1,
                        "resultsPerPage": 1
                    },
                    "items": [
                        {
                            "kind": "youtube#video",
                            "etag": "\"j6xRRd8dTPVVptg711_CSPADRfg/OH9HXaYO56_U6NhLgxG7iD488KY\"",
                            "id": "t7sNVRlr4CQ",
                            "statistics": {
                                "viewCount": "110262",
                                "likeCount": "388",
                                "dislikeCount": "233",
                                "favoriteCount": "0",
                                "commentCount": "153"
                            }
                        }
                    ]
                }
            }
        ],
        "originalQuery": "Ashley Judd: How online abuse of women has spiraled out of control"
    },
    {
        "kind": "youtube#searchListResponse",
        "etag": "\"j6xRRd8dTPVVptg711_CSPADRfg/3m-Ks_9nUtxt_j_PzZDGszjXyLc\"",
        "nextPageToken": "CAMQAA",
        "regionCode": "US",
        "pageInfo": {
            "totalResults": 113,
            "resultsPerPage": 3
        },
        "items": [
            {
                "kind": "youtube#searchResult",
                "etag": "\"j6xRRd8dTPVVptg711_CSPADRfg/L96lvirG4Zqo59o6ONgDIyH19Fc\"",
                "id": {
                    "kind": "youtube#video",
                    "videoId": "ulYR5bpu68E"
                },
                "snippet": {
                    "publishedAt": "2017-02-08T17:10:45.000Z",
                    "channelId": "UCAuUUnT6oDeKwE6v1NGQxug",
                    "title": "Art made of the air we breathe |  Emily Parsons-Lord",
                    "description": "Emily Parsons-Lord re-creates air from distinct moments in Earth's history -- from the clean, fresh-tasting air of the Carboniferous period to the soda-water air of ...",
                    "thumbnails": {
                        "default": {
                            "url": "https://i.ytimg.com/vi/ulYR5bpu68E/default.jpg",
                            "width": 120,
                            "height": 90
                        },
                        "medium": {
                            "url": "https://i.ytimg.com/vi/ulYR5bpu68E/mqdefault.jpg",
                            "width": 320,
                            "height": 180
                        },
                        "high": {
                            "url": "https://i.ytimg.com/vi/ulYR5bpu68E/hqdefault.jpg",
                            "width": 480,
                            "height": 360
                        }
                    },
                    "channelTitle": "TED",
                    "liveBroadcastContent": "none"
                },
                "stats": {
                    "kind": "youtube#videoListResponse",
                    "etag": "\"j6xRRd8dTPVVptg711_CSPADRfg/n5W8WaDeEiHH672BrBm-vpvEGYo\"",
                    "pageInfo": {
                        "totalResults": 1,
                        "resultsPerPage": 1
                    },
                    "items": [
                        {
                            "kind": "youtube#video",
                            "etag": "\"j6xRRd8dTPVVptg711_CSPADRfg/bH9gtYd1RVsUezSFXf5RT_3T24w\"",
                            "id": "ulYR5bpu68E",
                            "statistics": {
                                "viewCount": "74871",
                                "likeCount": "1020",
                                "dislikeCount": "248",
                                "favoriteCount": "0",
                                "commentCount": "119"
                            }
                        }
                    ]
                }
            },
            {
                "kind": "youtube#searchResult",
                "etag": "\"j6xRRd8dTPVVptg711_CSPADRfg/iJwtpZ_1rhBOIb6QFQ-C75zvkE0\"",
                "id": {
                    "kind": "youtube#video",
                    "videoId": "pysNMB033co"
                },
                "snippet": {
                    "publishedAt": "2016-06-29T22:04:50.000Z",
                    "channelId": "UCsT0YIqwnpJCM-mx7-gSA4Q",
                    "title": "Picturing the Air Around Us | Emily Parsons-Lord | TEDxYouth@Sydney",
                    "description": "Emily Parsons-Lord asks us to picture the air in our imagination. What do we see? Empty space, clear blue sly or trees dancing in the breeze? We tend not to ...",
                    "thumbnails": {
                        "default": {
                            "url": "https://i.ytimg.com/vi/pysNMB033co/default.jpg",
                            "width": 120,
                            "height": 90
                        },
                        "medium": {
                            "url": "https://i.ytimg.com/vi/pysNMB033co/mqdefault.jpg",
                            "width": 320,
                            "height": 180
                        },
                        "high": {
                            "url": "https://i.ytimg.com/vi/pysNMB033co/hqdefault.jpg",
                            "width": 480,
                            "height": 360
                        }
                    },
                    "channelTitle": "TEDx Talks",
                    "liveBroadcastContent": "none"
                },
                "stats": {
                    "kind": "youtube#videoListResponse",
                    "etag": "\"j6xRRd8dTPVVptg711_CSPADRfg/WybyijP2MIhnL60OHg6KYq_BdyY\"",
                    "pageInfo": {
                        "totalResults": 1,
                        "resultsPerPage": 1
                    },
                    "items": [
                        {
                            "kind": "youtube#video",
                            "etag": "\"j6xRRd8dTPVVptg711_CSPADRfg/IPG4ynUx9O4iJYpefoDHYR15C98\"",
                            "id": "pysNMB033co",
                            "statistics": {
                                "viewCount": "705",
                                "likeCount": "5",
                                "dislikeCount": "0",
                                "favoriteCount": "0",
                                "commentCount": "0"
                            }
                        }
                    ]
                }
            },
            {
                "kind": "youtube#searchResult",
                "etag": "\"j6xRRd8dTPVVptg711_CSPADRfg/UAhvUzaOU5IM-M_7DIPuGrGnhNk\"",
                "id": {
                    "kind": "youtube#video",
                    "videoId": "gXDAGYLu3X8"
                },
                "snippet": {
                    "publishedAt": "2019-06-11T16:08:44.000Z",
                    "channelId": "UCsT0YIqwnpJCM-mx7-gSA4Q",
                    "title": "The air we breathe is killing us — but it doesn’t have to | Beth Gardiner | TEDxLondon",
                    "description": "Breathing is the most universal experience there is. But in too many places, it carries a hidden danger. Scientists have linked air pollution to a long and growing ...",
                    "thumbnails": {
                        "default": {
                            "url": "https://i.ytimg.com/vi/gXDAGYLu3X8/default.jpg",
                            "width": 120,
                            "height": 90
                        },
                        "medium": {
                            "url": "https://i.ytimg.com/vi/gXDAGYLu3X8/mqdefault.jpg",
                            "width": 320,
                            "height": 180
                        },
                        "high": {
                            "url": "https://i.ytimg.com/vi/gXDAGYLu3X8/hqdefault.jpg",
                            "width": 480,
                            "height": 360
                        }
                    },
                    "channelTitle": "TEDx Talks",
                    "liveBroadcastContent": "none"
                },
                "stats": {
                    "kind": "youtube#videoListResponse",
                    "etag": "\"j6xRRd8dTPVVptg711_CSPADRfg/I5TpFv9a17wE5K-mImFuWXAlctk\"",
                    "pageInfo": {
                        "totalResults": 1,
                        "resultsPerPage": 1
                    },
                    "items": [
                        {
                            "kind": "youtube#video",
                            "etag": "\"j6xRRd8dTPVVptg711_CSPADRfg/KNqtY2hbNEC6e2MDDV_YUI3456M\"",
                            "id": "gXDAGYLu3X8",
                            "statistics": {
                                "viewCount": "396",
                                "likeCount": "4",
                                "dislikeCount": "0",
                                "favoriteCount": "0",
                                "commentCount": "0"
                            }
                        }
                    ]
                }
            }
        ],
        "originalQuery": "Emily Parsons Lord: Art made of the air we breathe"
    },
    {
        "kind": "youtube#searchListResponse",
        "etag": "\"j6xRRd8dTPVVptg711_CSPADRfg/ejB0D3vYMxhjrlBJumqKObWZ42g\"",
        "nextPageToken": "CAMQAA",
        "regionCode": "US",
        "pageInfo": {
            "totalResults": 798,
            "resultsPerPage": 3
        },
        "items": [
            {
                "kind": "youtube#searchResult",
                "etag": "\"j6xRRd8dTPVVptg711_CSPADRfg/yqMOqncXItYzSYwajMQMZh0KY4Y\"",
                "id": {
                    "kind": "youtube#video",
                    "videoId": "6V6p1tgHfm0"
                },
                "snippet": {
                    "publishedAt": "2017-02-09T17:08:41.000Z",
                    "channelId": "UCAuUUnT6oDeKwE6v1NGQxug",
                    "title": "How to have better political conversations | Robb Willer",
                    "description": "Robb Willer studies the forces that unite and divide us. As a social psychologist, he researches how moral values -- typically a source of division -- can also be ...",
                    "thumbnails": {
                        "default": {
                            "url": "https://i.ytimg.com/vi/6V6p1tgHfm0/default.jpg",
                            "width": 120,
                            "height": 90
                        },
                        "medium": {
                            "url": "https://i.ytimg.com/vi/6V6p1tgHfm0/mqdefault.jpg",
                            "width": 320,
                            "height": 180
                        },
                        "high": {
                            "url": "https://i.ytimg.com/vi/6V6p1tgHfm0/hqdefault.jpg",
                            "width": 480,
                            "height": 360
                        }
                    },
                    "channelTitle": "TED",
                    "liveBroadcastContent": "none"
                },
                "stats": {
                    "kind": "youtube#videoListResponse",
                    "etag": "\"j6xRRd8dTPVVptg711_CSPADRfg/ny5IEID4EAYoM-k52KiRyfHWLaw\"",
                    "pageInfo": {
                        "totalResults": 1,
                        "resultsPerPage": 1
                    },
                    "items": [
                        {
                            "kind": "youtube#video",
                            "etag": "\"j6xRRd8dTPVVptg711_CSPADRfg/oKrV70pBxIt8Ek183Y0rQJM5MCc\"",
                            "id": "6V6p1tgHfm0",
                            "statistics": {
                                "viewCount": "166530",
                                "likeCount": "3700",
                                "dislikeCount": "172",
                                "favoriteCount": "0",
                                "commentCount": "476"
                            }
                        }
                    ]
                }
            },
            {
                "kind": "youtube#searchResult",
                "etag": "\"j6xRRd8dTPVVptg711_CSPADRfg/NW3kkKuDqpy1OcNodU7BgGYaquU\"",
                "id": {
                    "kind": "youtube#video",
                    "videoId": "5LrThf-Beq0"
                },
                "snippet": {
                    "publishedAt": "2016-11-01T18:21:08.000Z",
                    "channelId": "UCsT0YIqwnpJCM-mx7-gSA4Q",
                    "title": "How to Fix Our Broken Political Conversations | Robb Willer | TEDxMarin",
                    "description": "Compelling new research on language offers a response to political polarization. What if new social psychology research held the key to bridging America's ...",
                    "thumbnails": {
                        "default": {
                            "url": "https://i.ytimg.com/vi/5LrThf-Beq0/default.jpg",
                            "width": 120,
                            "height": 90
                        },
                        "medium": {
                            "url": "https://i.ytimg.com/vi/5LrThf-Beq0/mqdefault.jpg",
                            "width": 320,
                            "height": 180
                        },
                        "high": {
                            "url": "https://i.ytimg.com/vi/5LrThf-Beq0/hqdefault.jpg",
                            "width": 480,
                            "height": 360
                        }
                    },
                    "channelTitle": "TEDx Talks",
                    "liveBroadcastContent": "none"
                },
                "stats": {
                    "kind": "youtube#videoListResponse",
                    "etag": "\"j6xRRd8dTPVVptg711_CSPADRfg/7FKLB1xT-qTdMHlpjxjCQR6veac\"",
                    "pageInfo": {
                        "totalResults": 1,
                        "resultsPerPage": 1
                    },
                    "items": [
                        {
                            "kind": "youtube#video",
                            "etag": "\"j6xRRd8dTPVVptg711_CSPADRfg/A7QYtd81E4xCd0WY-jVcT3a_FDc\"",
                            "id": "5LrThf-Beq0",
                            "statistics": {
                                "viewCount": "25195",
                                "likeCount": "332",
                                "dislikeCount": "23",
                                "favoriteCount": "0",
                                "commentCount": "44"
                            }
                        }
                    ]
                }
            },
            {
                "kind": "youtube#searchResult",
                "etag": "\"j6xRRd8dTPVVptg711_CSPADRfg/TvpvTvc-g7jdkP4ycquIPPDtIas\"",
                "id": {
                    "kind": "youtube#video",
                    "videoId": "bLv56-EMbn4"
                },
                "snippet": {
                    "publishedAt": "2017-03-03T20:00:03.000Z",
                    "channelId": "UCdY3DRovj1Kk6Ar0Za91vZw",
                    "title": "Better Political Conversations",
                    "description": "Andrew sits down with Robb Willer, P.h.D. to talk about how to have better conversations with people you disagree with Catch up on past episodes at ...",
                    "thumbnails": {
                        "default": {
                            "url": "https://i.ytimg.com/vi/bLv56-EMbn4/default.jpg",
                            "width": 120,
                            "height": 90
                        },
                        "medium": {
                            "url": "https://i.ytimg.com/vi/bLv56-EMbn4/mqdefault.jpg",
                            "width": 320,
                            "height": 180
                        },
                        "high": {
                            "url": "https://i.ytimg.com/vi/bLv56-EMbn4/hqdefault.jpg",
                            "width": 480,
                            "height": 360
                        }
                    },
                    "channelTitle": "Untold",
                    "liveBroadcastContent": "none"
                },
                "stats": {
                    "kind": "youtube#videoListResponse",
                    "etag": "\"j6xRRd8dTPVVptg711_CSPADRfg/SQ0_wS4FI3AgvCekZpV5yvqHGY8\"",
                    "pageInfo": {
                        "totalResults": 1,
                        "resultsPerPage": 1
                    },
                    "items": [
                        {
                            "kind": "youtube#video",
                            "etag": "\"j6xRRd8dTPVVptg711_CSPADRfg/VT3dcKimPeLtS9vhdFpSZDwfoL0\"",
                            "id": "bLv56-EMbn4",
                            "statistics": {
                                "viewCount": "295",
                                "likeCount": "8",
                                "dislikeCount": "1",
                                "favoriteCount": "0",
                                "commentCount": "0"
                            }
                        }
                    ]
                }
            }
        ],
        "originalQuery": "Robb Willer: How to have better political conversations"
    },
    {
        "kind": "youtube#searchListResponse",
        "etag": "\"j6xRRd8dTPVVptg711_CSPADRfg/sLAAa99RwLEuORfBj4gr_DYcR7s\"",
        "nextPageToken": "CAMQAA",
        "regionCode": "US",
        "pageInfo": {
            "totalResults": 1788,
            "resultsPerPage": 3
        },
        "items": [
            {
                "kind": "youtube#searchResult",
                "etag": "\"j6xRRd8dTPVVptg711_CSPADRfg/YxtfRa4EmDLpNKau2RsBiCMNyCA\"",
                "id": {
                    "kind": "youtube#video",
                    "videoId": "nOHbn8Q1fBM"
                },
                "snippet": {
                    "publishedAt": "2017-02-10T16:49:48.000Z",
                    "channelId": "UCAuUUnT6oDeKwE6v1NGQxug",
                    "title": "The ethical dilemma of designer babies | Paul Knoepfler",
                    "description": "Creating genetically modified children is no longer a science fiction fantasy; it's a likely future scenario. Biologist Paul Knoepfler estimates that within fifteen ...",
                    "thumbnails": {
                        "default": {
                            "url": "https://i.ytimg.com/vi/nOHbn8Q1fBM/default.jpg",
                            "width": 120,
                            "height": 90
                        },
                        "medium": {
                            "url": "https://i.ytimg.com/vi/nOHbn8Q1fBM/mqdefault.jpg",
                            "width": 320,
                            "height": 180
                        },
                        "high": {
                            "url": "https://i.ytimg.com/vi/nOHbn8Q1fBM/hqdefault.jpg",
                            "width": 480,
                            "height": 360
                        }
                    },
                    "channelTitle": "TED",
                    "liveBroadcastContent": "none"
                },
                "stats": {
                    "kind": "youtube#videoListResponse",
                    "etag": "\"j6xRRd8dTPVVptg711_CSPADRfg/kwzpwufG_GlzX363khmFOYRyOec\"",
                    "pageInfo": {
                        "totalResults": 1,
                        "resultsPerPage": 1
                    },
                    "items": [
                        {
                            "kind": "youtube#video",
                            "etag": "\"j6xRRd8dTPVVptg711_CSPADRfg/xrdlEXnUQmGf9vGA_KWSYFlrFYg\"",
                            "id": "nOHbn8Q1fBM",
                            "statistics": {
                                "viewCount": "217828",
                                "likeCount": "3266",
                                "dislikeCount": "511",
                                "favoriteCount": "0",
                                "commentCount": "847"
                            }
                        }
                    ]
                }
            },
            {
                "kind": "youtube#searchResult",
                "etag": "\"j6xRRd8dTPVVptg711_CSPADRfg/2xMbsze6C1B7KpenCAlqF4IICkw\"",
                "id": {
                    "kind": "youtube#video",
                    "videoId": "_YpACFaK0O4"
                },
                "snippet": {
                    "publishedAt": "2018-11-30T00:10:26.000Z",
                    "channelId": "UC-Nnu2-eKA0aRYrCSx3kHDQ",
                    "title": "Ethical concerns surrounding gene-edited babies",
                    "description": "A scientist's announcement of two genetically edited babies in China sparked both safety and ethical concerns in the scientific community. Malia Fullerton, an ...",
                    "thumbnails": {
                        "default": {
                            "url": "https://i.ytimg.com/vi/_YpACFaK0O4/default.jpg",
                            "width": 120,
                            "height": 90
                        },
                        "medium": {
                            "url": "https://i.ytimg.com/vi/_YpACFaK0O4/mqdefault.jpg",
                            "width": 320,
                            "height": 180
                        },
                        "high": {
                            "url": "https://i.ytimg.com/vi/_YpACFaK0O4/hqdefault.jpg",
                            "width": 480,
                            "height": 360
                        }
                    },
                    "channelTitle": "UW Medicine",
                    "liveBroadcastContent": "none"
                },
                "stats": {
                    "kind": "youtube#videoListResponse",
                    "etag": "\"j6xRRd8dTPVVptg711_CSPADRfg/Wkjr-Xcj8l6Qr4fSgrO0ZXgu7-8\"",
                    "pageInfo": {
                        "totalResults": 1,
                        "resultsPerPage": 1
                    },
                    "items": [
                        {
                            "kind": "youtube#video",
                            "etag": "\"j6xRRd8dTPVVptg711_CSPADRfg/qil6DsdFwP_MpFWbVA8ebbMvgMk\"",
                            "id": "_YpACFaK0O4",
                            "statistics": {
                                "viewCount": "5835",
                                "likeCount": "55",
                                "dislikeCount": "5",
                                "favoriteCount": "0",
                                "commentCount": "0"
                            }
                        }
                    ]
                }
            },
            {
                "kind": "youtube#searchResult",
                "etag": "\"j6xRRd8dTPVVptg711_CSPADRfg/UtoOfsSD5WTUHENbaQNb_PFT5F0\"",
                "id": {
                    "kind": "youtube#video",
                    "videoId": "JY3ZPsOxHyU"
                },
                "snippet": {
                    "publishedAt": "2016-02-29T14:23:04.000Z",
                    "channelId": "UCOzWn948D9YO41K3G7vl_Zg",
                    "title": "Ethics of Human Gene Editing",
                    "description": "For millennia people have tried to influence what we would now call the genetic qualities of the human species, but technological limitations have long stymied ...",
                    "thumbnails": {
                        "default": {
                            "url": "https://i.ytimg.com/vi/JY3ZPsOxHyU/default.jpg",
                            "width": 120,
                            "height": 90
                        },
                        "medium": {
                            "url": "https://i.ytimg.com/vi/JY3ZPsOxHyU/mqdefault.jpg",
                            "width": 320,
                            "height": 180
                        },
                        "high": {
                            "url": "https://i.ytimg.com/vi/JY3ZPsOxHyU/hqdefault.jpg",
                            "width": 480,
                            "height": 360
                        }
                    },
                    "channelTitle": "Distinctive Voices",
                    "liveBroadcastContent": "none"
                },
                "stats": {
                    "kind": "youtube#videoListResponse",
                    "etag": "\"j6xRRd8dTPVVptg711_CSPADRfg/k5oB0ND46f_6qXK0vjM79lWCtas\"",
                    "pageInfo": {
                        "totalResults": 1,
                        "resultsPerPage": 1
                    },
                    "items": [
                        {
                            "kind": "youtube#video",
                            "etag": "\"j6xRRd8dTPVVptg711_CSPADRfg/0krdmuxjrTFfBoRXv6of3afjxco\"",
                            "id": "JY3ZPsOxHyU",
                            "statistics": {
                                "viewCount": "6529",
                                "likeCount": "66",
                                "dislikeCount": "6",
                                "favoriteCount": "0",
                                "commentCount": "5"
                            }
                        }
                    ]
                }
            }
        ],
        "originalQuery": "Paul Knoepfler: The ethical dilemma of designer babies"
    },
    {
        "kind": "youtube#searchListResponse",
        "etag": "\"j6xRRd8dTPVVptg711_CSPADRfg/C4EN9cAUIj61O03OIe7L3Cu67_A\"",
        "nextPageToken": "CAMQAA",
        "regionCode": "US",
        "pageInfo": {
            "totalResults": 2123,
            "resultsPerPage": 3
        },
        "items": [
            {
                "kind": "youtube#searchResult",
                "etag": "\"j6xRRd8dTPVVptg711_CSPADRfg/mFHnq88wOIQ5sRCj1oB85VU51J8\"",
                "id": {
                    "kind": "youtube#video",
                    "videoId": "E_fB_s_TC5k"
                },
                "snippet": {
                    "publishedAt": "2017-02-14T18:06:25.000Z",
                    "channelId": "UCAuUUnT6oDeKwE6v1NGQxug",
                    "title": "Buildings that blend nature and city | Jeanne Gang",
                    "description": "A skyscraper that channels the breeze ... a building that creates community around a hearth ... Jeanne Gang uses architecture to build relationships. In this ...",
                    "thumbnails": {
                        "default": {
                            "url": "https://i.ytimg.com/vi/E_fB_s_TC5k/default.jpg",
                            "width": 120,
                            "height": 90
                        },
                        "medium": {
                            "url": "https://i.ytimg.com/vi/E_fB_s_TC5k/mqdefault.jpg",
                            "width": 320,
                            "height": 180
                        },
                        "high": {
                            "url": "https://i.ytimg.com/vi/E_fB_s_TC5k/hqdefault.jpg",
                            "width": 480,
                            "height": 360
                        }
                    },
                    "channelTitle": "TED",
                    "liveBroadcastContent": "none"
                },
                "stats": {
                    "kind": "youtube#videoListResponse",
                    "etag": "\"j6xRRd8dTPVVptg711_CSPADRfg/hykRHU1vKoQt6H0ac78PBEmojYs\"",
                    "pageInfo": {
                        "totalResults": 1,
                        "resultsPerPage": 1
                    },
                    "items": [
                        {
                            "kind": "youtube#video",
                            "etag": "\"j6xRRd8dTPVVptg711_CSPADRfg/_q-2k6hGKV_Um5VXuB6IX44BdNY\"",
                            "id": "E_fB_s_TC5k",
                            "statistics": {
                                "viewCount": "206883",
                                "likeCount": "5687",
                                "dislikeCount": "260",
                                "favoriteCount": "0",
                                "commentCount": "286"
                            }
                        }
                    ]
                }
            },
            {
                "kind": "youtube#searchResult",
                "etag": "\"j6xRRd8dTPVVptg711_CSPADRfg/AlG4FSRCd2LMgugI-j2VnXfAup8\"",
                "id": {
                    "kind": "youtube#video",
                    "videoId": "ECP8S-Z7xe8"
                },
                "snippet": {
                    "publishedAt": "2014-03-08T03:50:55.000Z",
                    "channelId": "UCsT0YIqwnpJCM-mx7-gSA4Q",
                    "title": "Building communities through architecture: Jeanne Gang at TEDxMidwest",
                    "description": "MacArthur Prize winning architect, Jeanne Gang enlightens the audience as to the significant role that architecture plays in building communities. From Aqua (an ...",
                    "thumbnails": {
                        "default": {
                            "url": "https://i.ytimg.com/vi/ECP8S-Z7xe8/default.jpg",
                            "width": 120,
                            "height": 90
                        },
                        "medium": {
                            "url": "https://i.ytimg.com/vi/ECP8S-Z7xe8/mqdefault.jpg",
                            "width": 320,
                            "height": 180
                        },
                        "high": {
                            "url": "https://i.ytimg.com/vi/ECP8S-Z7xe8/hqdefault.jpg",
                            "width": 480,
                            "height": 360
                        }
                    },
                    "channelTitle": "TEDx Talks",
                    "liveBroadcastContent": "none"
                },
                "stats": {
                    "kind": "youtube#videoListResponse",
                    "etag": "\"j6xRRd8dTPVVptg711_CSPADRfg/-gOIP8G2-h6WkH3pNQJaNQusPnc\"",
                    "pageInfo": {
                        "totalResults": 1,
                        "resultsPerPage": 1
                    },
                    "items": [
                        {
                            "kind": "youtube#video",
                            "etag": "\"j6xRRd8dTPVVptg711_CSPADRfg/WB00THHFdT1vMSqq3RkcMe-bf68\"",
                            "id": "ECP8S-Z7xe8",
                            "statistics": {
                                "viewCount": "19255",
                                "likeCount": "263",
                                "dislikeCount": "9",
                                "favoriteCount": "0",
                                "commentCount": "2"
                            }
                        }
                    ]
                }
            },
            {
                "kind": "youtube#searchResult",
                "etag": "\"j6xRRd8dTPVVptg711_CSPADRfg/3w5ybz4EQ6qZS13gBZEC3hS6Hbc\"",
                "id": {
                    "kind": "youtube#video",
                    "videoId": "Bu-kGoEuuPY"
                },
                "snippet": {
                    "publishedAt": "2015-10-09T10:34:07.000Z",
                    "channelId": "UCsWG9ANbrmgR0z-eFk_A3YQ",
                    "title": "Jeanne Gang explains her design intent for Chicago&#39;s Vista skyscraper in new video",
                    "description": "In a newly released video, American architect Jeanne Gang explains how natural crystal formations inspired her design of Vista Residences, a new residential ...",
                    "thumbnails": {
                        "default": {
                            "url": "https://i.ytimg.com/vi/Bu-kGoEuuPY/default.jpg",
                            "width": 120,
                            "height": 90
                        },
                        "medium": {
                            "url": "https://i.ytimg.com/vi/Bu-kGoEuuPY/mqdefault.jpg",
                            "width": 320,
                            "height": 180
                        },
                        "high": {
                            "url": "https://i.ytimg.com/vi/Bu-kGoEuuPY/hqdefault.jpg",
                            "width": 480,
                            "height": 360
                        }
                    },
                    "channelTitle": "Dezeen",
                    "liveBroadcastContent": "none"
                },
                "stats": {
                    "kind": "youtube#videoListResponse",
                    "etag": "\"j6xRRd8dTPVVptg711_CSPADRfg/dh-oHcb6Hf0mLtOutijS7TIaP5g\"",
                    "pageInfo": {
                        "totalResults": 1,
                        "resultsPerPage": 1
                    },
                    "items": [
                        {
                            "kind": "youtube#video",
                            "etag": "\"j6xRRd8dTPVVptg711_CSPADRfg/KYoRiJ6a4f4PMaSrM-e0J2xanSg\"",
                            "id": "Bu-kGoEuuPY",
                            "statistics": {
                                "viewCount": "13129",
                                "likeCount": "37",
                                "dislikeCount": "2",
                                "favoriteCount": "0",
                                "commentCount": "2"
                            }
                        }
                    ]
                }
            }
        ],
        "originalQuery": "Jeanne Gang: Buildings that blend nature and city"
    },
    {
        "kind": "youtube#searchListResponse",
        "etag": "\"j6xRRd8dTPVVptg711_CSPADRfg/9CcyKgOn1Z9XO9CDg8iCW46jzJE\"",
        "nextPageToken": "CAMQAA",
        "regionCode": "US",
        "pageInfo": {
            "totalResults": 1299,
            "resultsPerPage": 3
        },
        "items": [
            {
                "kind": "youtube#searchResult",
                "etag": "\"j6xRRd8dTPVVptg711_CSPADRfg/i4-d1-8Tri2QeSnim4xpR__CVUg\"",
                "id": {
                    "kind": "youtube#video",
                    "videoId": "FqrLUtIFVjs"
                },
                "snippet": {
                    "publishedAt": "2017-02-15T16:10:22.000Z",
                    "channelId": "UCAuUUnT6oDeKwE6v1NGQxug",
                    "title": "Where is cybercrime really coming from? | Caleb Barlow",
                    "description": "Cybercrime netted a whopping $450 billion in profits last year, with 2 billion records lost or stolen worldwide. Security expert Caleb Barlow calls out the ...",
                    "thumbnails": {
                        "default": {
                            "url": "https://i.ytimg.com/vi/FqrLUtIFVjs/default.jpg",
                            "width": 120,
                            "height": 90
                        },
                        "medium": {
                            "url": "https://i.ytimg.com/vi/FqrLUtIFVjs/mqdefault.jpg",
                            "width": 320,
                            "height": 180
                        },
                        "high": {
                            "url": "https://i.ytimg.com/vi/FqrLUtIFVjs/hqdefault.jpg",
                            "width": 480,
                            "height": 360
                        }
                    },
                    "channelTitle": "TED",
                    "liveBroadcastContent": "none"
                },
                "stats": {
                    "kind": "youtube#videoListResponse",
                    "etag": "\"j6xRRd8dTPVVptg711_CSPADRfg/F7MKxBCl5KtSiNrQAMBPVoxDeKs\"",
                    "pageInfo": {
                        "totalResults": 1,
                        "resultsPerPage": 1
                    },
                    "items": [
                        {
                            "kind": "youtube#video",
                            "etag": "\"j6xRRd8dTPVVptg711_CSPADRfg/KyCdEDN7Z_7Wvz5cD9kVrOcJXL8\"",
                            "id": "FqrLUtIFVjs",
                            "statistics": {
                                "viewCount": "242094",
                                "likeCount": "3584",
                                "dislikeCount": "287",
                                "favoriteCount": "0",
                                "commentCount": "326"
                            }
                        }
                    ]
                }
            },
            {
                "kind": "youtube#searchResult",
                "etag": "\"j6xRRd8dTPVVptg711_CSPADRfg/cRKxMy47PVUd6Cl0qdF-QeAXCIM\"",
                "id": {
                    "kind": "youtube#video",
                    "videoId": "-OyS0oSnKoo"
                },
                "snippet": {
                    "publishedAt": "2017-02-16T06:46:11.000Z",
                    "channelId": "UCoRmlutNQvJqSj9kD0BYv_g",
                    "title": "Where is cybercrime really coming from  Caleb Barlow",
                    "description": "",
                    "thumbnails": {
                        "default": {
                            "url": "https://i.ytimg.com/vi/-OyS0oSnKoo/default.jpg",
                            "width": 120,
                            "height": 90
                        },
                        "medium": {
                            "url": "https://i.ytimg.com/vi/-OyS0oSnKoo/mqdefault.jpg",
                            "width": 320,
                            "height": 180
                        },
                        "high": {
                            "url": "https://i.ytimg.com/vi/-OyS0oSnKoo/hqdefault.jpg",
                            "width": 480,
                            "height": 360
                        }
                    },
                    "channelTitle": "MKT Online",
                    "liveBroadcastContent": "none"
                },
                "stats": {
                    "kind": "youtube#videoListResponse",
                    "etag": "\"j6xRRd8dTPVVptg711_CSPADRfg/WKNcKG2xI9qAcoOkIu5vmCbL5cU\"",
                    "pageInfo": {
                        "totalResults": 1,
                        "resultsPerPage": 1
                    },
                    "items": [
                        {
                            "kind": "youtube#video",
                            "etag": "\"j6xRRd8dTPVVptg711_CSPADRfg/S_4CSgikIiqjJoe94DeZW2akrW4\"",
                            "id": "-OyS0oSnKoo",
                            "statistics": {
                                "viewCount": "174",
                                "likeCount": "0",
                                "dislikeCount": "0",
                                "favoriteCount": "0",
                                "commentCount": "0"
                            }
                        }
                    ]
                }
            },
            {
                "kind": "youtube#searchResult",
                "etag": "\"j6xRRd8dTPVVptg711_CSPADRfg/8etB-2LpEeGflMrdz02cl-zZq4U\"",
                "id": {
                    "kind": "youtube#video",
                    "videoId": "9AEWetHAbKA"
                },
                "snippet": {
                    "publishedAt": "2018-09-18T12:58:51.000Z",
                    "channelId": "UCWrXlzhIENTJrAuKVuPgdEA",
                    "title": "IBM&#39;s Caleb Barlow: How Businesses Need to Respond to Cyberattacks Under GDPR",
                    "description": "Europe's GDPR rules mean cybersecurity breaches need to be reported to regulators within 72 hours of them being discovered. IBM Security's vice president ...",
                    "thumbnails": {
                        "default": {
                            "url": "https://i.ytimg.com/vi/9AEWetHAbKA/default.jpg",
                            "width": 120,
                            "height": 90
                        },
                        "medium": {
                            "url": "https://i.ytimg.com/vi/9AEWetHAbKA/mqdefault.jpg",
                            "width": 320,
                            "height": 180
                        },
                        "high": {
                            "url": "https://i.ytimg.com/vi/9AEWetHAbKA/hqdefault.jpg",
                            "width": 480,
                            "height": 360
                        }
                    },
                    "channelTitle": "WIRED UK",
                    "liveBroadcastContent": "none"
                },
                "stats": {
                    "kind": "youtube#videoListResponse",
                    "etag": "\"j6xRRd8dTPVVptg711_CSPADRfg/R1ju3OCw9zzeutEBNWR6T6_Ygpg\"",
                    "pageInfo": {
                        "totalResults": 1,
                        "resultsPerPage": 1
                    },
                    "items": [
                        {
                            "kind": "youtube#video",
                            "etag": "\"j6xRRd8dTPVVptg711_CSPADRfg/1MkXyb0CqlsEQaDHD7wVBVWAyAY\"",
                            "id": "9AEWetHAbKA",
                            "statistics": {
                                "viewCount": "1442",
                                "likeCount": "13",
                                "dislikeCount": "1",
                                "favoriteCount": "0",
                                "commentCount": "1"
                            }
                        }
                    ]
                }
            }
        ],
        "originalQuery": "Caleb Barlow: Where is cybercrime really coming from?"
    },
    {
        "kind": "youtube#searchListResponse",
        "etag": "\"j6xRRd8dTPVVptg711_CSPADRfg/b8aTkqssnmbSVIHsgvgw3x8s3P0\"",
        "nextPageToken": "CAMQAA",
        "regionCode": "US",
        "pageInfo": {
            "totalResults": 653,
            "resultsPerPage": 3
        },
        "items": [
            {
                "kind": "youtube#searchResult",
                "etag": "\"j6xRRd8dTPVVptg711_CSPADRfg/ItAoKxZ8gGt1PV69GHrNZ1BpWfo\"",
                "id": {
                    "kind": "youtube#video",
                    "videoId": "0_W0HFy9Et4"
                },
                "snippet": {
                    "publishedAt": "2016-05-13T17:43:06.000Z",
                    "channelId": "UCsT0YIqwnpJCM-mx7-gSA4Q",
                    "title": "What We Don’t Know About Europe’s Muslim Kids and Why We Should Care | Deeyah Khan | TEDxExeter",
                    "description": "Aged 17, Deeyah fled from Norway confused, lost and torn between cultures. Unlike some young Muslims she picked up a camera instead of a gun. She now ...",
                    "thumbnails": {
                        "default": {
                            "url": "https://i.ytimg.com/vi/0_W0HFy9Et4/default.jpg",
                            "width": 120,
                            "height": 90
                        },
                        "medium": {
                            "url": "https://i.ytimg.com/vi/0_W0HFy9Et4/mqdefault.jpg",
                            "width": 320,
                            "height": 180
                        },
                        "high": {
                            "url": "https://i.ytimg.com/vi/0_W0HFy9Et4/hqdefault.jpg",
                            "width": 480,
                            "height": 360
                        }
                    },
                    "channelTitle": "TEDx Talks",
                    "liveBroadcastContent": "none"
                },
                "stats": {
                    "kind": "youtube#videoListResponse",
                    "etag": "\"j6xRRd8dTPVVptg711_CSPADRfg/NOzKtMYi37snqdiOzFmqu9b4StU\"",
                    "pageInfo": {
                        "totalResults": 1,
                        "resultsPerPage": 1
                    },
                    "items": [
                        {
                            "kind": "youtube#video",
                            "etag": "\"j6xRRd8dTPVVptg711_CSPADRfg/4pWdNqD9XHE_uxNwvzen060-oBY\"",
                            "id": "0_W0HFy9Et4",
                            "statistics": {
                                "viewCount": "1002396",
                                "likeCount": "22512",
                                "dislikeCount": "2542",
                                "favoriteCount": "0",
                                "commentCount": "5005"
                            }
                        }
                    ]
                }
            },
            {
                "kind": "youtube#searchResult",
                "etag": "\"j6xRRd8dTPVVptg711_CSPADRfg/KTCyfM9SMXz_vwit_bYPns4FiT8\"",
                "id": {
                    "kind": "youtube#video",
                    "videoId": "WJo98LfIfEA"
                },
                "snippet": {
                    "publishedAt": "2017-02-16T19:11:51.000Z",
                    "channelId": "UCAuUUnT6oDeKwE6v1NGQxug",
                    "title": "What we don&#39;t know about Europe&#39;s Muslim kids | Deeyah Khan",
                    "description": "As the child of an Afghan mother and Pakistani father raised in Norway, Deeyah Khan knows what it's like to be a young person stuck between your community ...",
                    "thumbnails": {
                        "default": {
                            "url": "https://i.ytimg.com/vi/WJo98LfIfEA/default.jpg",
                            "width": 120,
                            "height": 90
                        },
                        "medium": {
                            "url": "https://i.ytimg.com/vi/WJo98LfIfEA/mqdefault.jpg",
                            "width": 320,
                            "height": 180
                        },
                        "high": {
                            "url": "https://i.ytimg.com/vi/WJo98LfIfEA/hqdefault.jpg",
                            "width": 480,
                            "height": 360
                        }
                    },
                    "channelTitle": "TED",
                    "liveBroadcastContent": "none"
                },
                "stats": {
                    "kind": "youtube#videoListResponse",
                    "etag": "\"j6xRRd8dTPVVptg711_CSPADRfg/xnXbPVKIWun6JyZoCE1trZKMs_c\"",
                    "pageInfo": {
                        "totalResults": 1,
                        "resultsPerPage": 1
                    },
                    "items": [
                        {
                            "kind": "youtube#video",
                            "etag": "\"j6xRRd8dTPVVptg711_CSPADRfg/d8RE5pmfmFuTAG-YNIIBCj9yWPk\"",
                            "id": "WJo98LfIfEA",
                            "statistics": {
                                "viewCount": "160605",
                                "favoriteCount": "0"
                            }
                        }
                    ]
                }
            },
            {
                "kind": "youtube#searchResult",
                "etag": "\"j6xRRd8dTPVVptg711_CSPADRfg/eDyG2OQr9OjYEWq6PKRW_qHJAVU\"",
                "id": {
                    "kind": "youtube#video",
                    "videoId": "05ZwgjQjnI0"
                },
                "snippet": {
                    "publishedAt": "2017-05-19T21:15:44.000Z",
                    "channelId": "UCsT0YIqwnpJCM-mx7-gSA4Q",
                    "title": "The Muslims You Cannot See | Sahar Habib Ghazi | TEDxStanford",
                    "description": "As an American Muslim journalist, Sahar often finds herself being \"othered\" because she doesn't fit into popular perception of what Muslims are, or, what she ...",
                    "thumbnails": {
                        "default": {
                            "url": "https://i.ytimg.com/vi/05ZwgjQjnI0/default.jpg",
                            "width": 120,
                            "height": 90
                        },
                        "medium": {
                            "url": "https://i.ytimg.com/vi/05ZwgjQjnI0/mqdefault.jpg",
                            "width": 320,
                            "height": 180
                        },
                        "high": {
                            "url": "https://i.ytimg.com/vi/05ZwgjQjnI0/hqdefault.jpg",
                            "width": 480,
                            "height": 360
                        }
                    },
                    "channelTitle": "TEDx Talks",
                    "liveBroadcastContent": "none"
                },
                "stats": {
                    "kind": "youtube#videoListResponse",
                    "etag": "\"j6xRRd8dTPVVptg711_CSPADRfg/i0nDVLEwl7ifuozzINHz6I7S4pw\"",
                    "pageInfo": {
                        "totalResults": 1,
                        "resultsPerPage": 1
                    },
                    "items": [
                        {
                            "kind": "youtube#video",
                            "etag": "\"j6xRRd8dTPVVptg711_CSPADRfg/zka7XRqRQwDecT48nHnTzx8U2_Y\"",
                            "id": "05ZwgjQjnI0",
                            "statistics": {
                                "viewCount": "514159",
                                "likeCount": "6897",
                                "dislikeCount": "909",
                                "favoriteCount": "0",
                                "commentCount": "1703"
                            }
                        }
                    ]
                }
            }
        ],
        "originalQuery": "Deeyah Khan: What we don't know about Europe's Muslim kids"
    }
]